{
  "symbol": "USD/CHF",
  "name": "US Dollar vs Swiss Franc",
  "nameCn": "美元/瑞郎",
  "timestamp": "2025-11-15T12:22:41.442Z",
  "price": {
    "close": "0.79374999",
    "high": "0.79438001",
    "low": "0.79321003",
    "open": "0.79395002",
    "change": "-0.02",
    "datetime": "2025-11-15 08:00:00"
  },
  "indicators": {
    "rsi": 54.10161,
    "macd": -8.3951137e-7,
    "macd_signal": -0.00045605797,
    "sma20": 0.792283
  },
  "analysis": {
    "zh": {
      "title": "美元/瑞郎技术分析：[震荡整理中]",
      "content": "当前美元/瑞郎（USD/CHF）在0.7937附近震荡整理，近期价格波动幅度较小，显示出市场缺乏明确的方向。虽然价格略有下跌，但整体趋势仍然较为平稳，未出现明显的趋势反转信号。\n\n从技术指标来看，RSI(14)数据缺失使得我们无法评估超买或超卖情况，但MACD指标显示出微弱的负值，暗示卖方力量可能略占上风。SMA(20)线位于0.7923，作为短期支撑位，若价格持续在此之上，可能会吸引买盘进入。\n\n支撑位方面，0.7923为关键支撑位，若跌破则可能进一步测试0.7910的心理关口。阻力位则在0.7944附近，若突破该位，可能会引发一波上涨行情。交易者应密切关注这些关键价位。\n\n建议交易者在当前震荡区间内采取观望态度，等待突破信号后再进行操作。若价格突破0.7944，可以考虑做多；若跌破0.7923，则应考虑做空，以控制风险。保持灵活应变，以应对市场的快速变化。"
    },
    "en": {
      "title": "US Dollar vs Swiss Franc Technical Analysis",
      "content": "The USD/CHF pair is currently trading at approximately 0.79375, reflecting a slight decline of 0.02% over the past 24 hours. The high and low for this period suggest a consolidative phase, with price action remaining tightly bound between 0.79438 and 0.79321. This range indicates a lack of momentum in the market, and traders should watch for a breakout above resistance at 0.7944 or below support at 0.7932 to gauge the next directional move.\n\nThe absence of RSI data limits our ability to definitively assess overbought or oversold conditions. However, the MACD indicates a bearish sentiment, as it currently sits at -0.00000083951137. If this trend continues, it may suggest further downside potential. A closer look at the 20-period Simple Moving Average (SMA) shows a level of 0.79228, which could act as a dynamic support if the price continues to decline. As the price approaches this SMA, caution is warranted, as a bounce off this level could present a buying opportunity.\n\nIn terms of support and resistance levels, the immediate support is established at 0.7932, while resistance appears to be at 0.7944. A decisive move beyond these levels could indicate the market's next bias. If the price breaks above 0.7944, it may target higher levels, possibly testing the 0.7950 mark. Conversely, a break below 0.7932 could lead to a further bearish move, potentially seeking the next support around 0.7920.\n\nFor traders, this range-bound market suggests a cautious approach. Employing a wait-and-see strategy may be prudent, as positioning for a breakout could yield favorable risk-reward ratios. If the price breaks above 0.7944, consider entering long positions, while a break below 0.7932 might warrant short positions, with stops placed strategically to manage risk effectively."
    }
  }
}